skxcs/__init__.py
skxcs/classifiers.py
skxcs/exceptions.py
skxcs-0.1.dist-info/LICENSE.txt
skxcs-0.1.dist-info/METADATA
skxcs-0.1.dist-info/WHEEL
skxcs-0.1.dist-info/top_level.txt
skxcs-0.1.dist-info/RECORD
