Metadata-Version: 2.1
Name: skxcs
Version: 0.1
Summary: SciKit learn wrapper for XCS algorithm implementation.
Home-page: UNKNOWN
Author: Jaroslav Michalovcik
Author-email: j.michalovcik@gmail.com
License: MIT
Keywords: XCS,xcs,SciKit,learn
Platform: UNKNOWN
Classifier: Programming Language :: Python :: 3
Classifier: License :: OSI Approved :: MIT License
Classifier: Operating System :: OS Independent
Classifier: Development Status :: 3 - Alpha
Classifier: Intended Audience :: Developers
Requires-Python: >=3.7
Requires-Dist: numpy
Requires-Dist: pandas
Requires-Dist: mdlp
Requires-Dist: sklearn
Requires-Dist: xcs
